lynie/__init__.py
lynie/lynie.py
lynie-1.0.4.dist-info/LICENSE
lynie-1.0.4.dist-info/METADATA
lynie-1.0.4.dist-info/WHEEL
lynie-1.0.4.dist-info/top_level.txt
lynie-1.0.4.dist-info/RECORD
