Metadata-Version: 2.1
Name: lynie
Version: 1.0.4
Summary: An easy to use python oneline-icator.
Home-page: https://github.com/jessatehcrow/lynie
Author: JessaTehCrow
Maintainer: JessaTehCrow
License: UNKNOWN
Keywords: python,one line,simple
Platform: UNKNOWN
